{
    "type": "IMPORT",
    "baseFontSize": "base",
    "typeScale": "minorThird",
    "spacing": "base",
    "radii": "base",
    "theme": "light",
    "distance": 0.02,
    "hue": 142,
    "saturation": 0.3,
    "primary": "green",
    "info": "cyan",
    "success": "green",
    "warning": "amber",
    "danger": "red",
    "red": 4,
    "amber": 25,
    "brown": 33,
    "green": 120,
    "teal": 180,
    "cyan": 200,
    "blue": 210,
    "indigo": 240,
    "violet": 260,
    "purple": 280,
    "pink": 340,
    "accentSaturation": 0.56,
    "accentMinLuminance": 0.1,
    "accentMidLuminance": 0.3,
    "accentMaxLuminance": 0.63,
    "singleCollection": false
}